[{"id":"1727847709473","productName":"HAHAH","category":"asdasd","price":"1000"},{"id":"1727847720110","productName":"asdasd","category":"Shoes","price":"we3r"},{"id":"1727847721417","productName":"asdasd","category":"Shoes","price":"we3r"},{"id":"1727847726723","productName":"asd","category":"Outer","price":"asd"},{"id":"1727847727399","productName":"asd","category":"Outer","price":"asd"},{"id":"1727847727704","productName":"asd","category":"Outer","price":"asd"},{"id":"1727847738805","productName":"HAHAH","category":"asdasd","price":"1000"},{"id":"1727847739937","productName":"HAHAH","category":"asdasd","price":"1000"},{"id":"1727847784460","productName":"a","category":"Outer","price":"a"},{"id":"1727847785266","productName":"a","category":"Outer","price":"a"},{"id":"1727847785745","productName":"a","category":"Outer","price":"a"},{"id":"1727847786068","productName":"a","category":"Outer","price":"a"},{"id":"1727847875628","productName":"a","category":"Outer","price":"a"},{"id":"1727847876415","productName":"a","category":"Outer","price":"a"},{"id":"1727847876900","productName":"a","category":"Outer","price":"a"},{"id":"1727847877167","productName":"a","category":"Outer","price":"a"},{"id":"1727847882739","productName":"asd","category":"Outer","price":"asd"},{"id":"1727847883747","productName":"asd","category":"Outer","price":"asd"},{"id":"1727847884588","productName":"asd","category":"Outer","price":"asd"},{"id":"1727847884953","productName":"asd","category":"Outer","price":"asd"},{"id":"1727848062245","productName":"asd","category":"Outer","price":"asd"},{"id":"1727848066333","productName":"asdasd","category":"Outer","price":"asdasd"},{"id":"1727848066815","productName":"asdasd","category":"Outer","price":"asdasd"},{"id":"1727848066978","productName":"asdasd","category":"Outer","price":"asdasd"},{"id":"1727848067148","productName":"asdasd","category":"Outer","price":"asdasd"},{"id":"1727848069705","productName":"asdasd","category":"Outer","price":"asdasd"},{"id":"1727848135193","productName":"asdasd","category":"Outer","price":"asdasd"},{"id":"1727848135345","productName":"asdasd","category":"Outer","price":"asdasd"},{"id":"1727848135706","productName":"asdasd","category":"Outer","price":"asdasd"},{"id":"1727848135860","productName":"asdasd","category":"Outer","price":"asdasd"},{"id":"1727848136015","productName":"asdasd","category":"Outer","price":"asdasd"},{"id":"1727848136147","productName":"asdasd","category":"Outer","price":"asdasd"},{"id":"1727848136319","productName":"asdasd","category":"Outer","price":"asdasd"},{"id":"1727848136483","productName":"asdasd","category":"Outer","price":"asdasd"},{"id":"1727848153427","productName":"asdasd","category":"Outer","price":"asdasd"},{"id":"1727848159155","productName":"asdasd","category":"Outer","price":"asdasdasdasd"},{"id":"1727848159665","productName":"asdasd","category":"Outer","price":"asdasdasdasd"},{"id":"1727848192811","productName":"asdasd","category":"Outer","price":"asdasdasdasd"},{"id":"1727848193076","productName":"asdasd","category":"Outer","price":"asdasdasdasd"},{"id":"1727848193230","productName":"asdasd","category":"Outer","price":"asdasdasdasd"},{"id":"1727848193401","productName":"asdasd","category":"Outer","price":"asdasdasdasd"},{"id":"1727848193549","productName":"asdasd","category":"Outer","price":"asdasdasdasd"},{"id":"1727848196764","productName":"asdasdasd","category":"Outer","price":"asdasdasdasdasd"},{"id":"1727848196910","productName":"asdasdasd","category":"Outer","price":"asdasdasdasdasd"},{"id":"1727848197081","productName":"asdasdasd","category":"Outer","price":"asdasdasdasdasd"},{"id":"1727848197305","productName":"asdasdasd","category":"Outer","price":"asdasdasdasdasd"},{"id":"1727848197459","productName":"asdasdasd","category":"Outer","price":"asdasdasdasdasd"},{"id":"1727848197631","productName":"asdasdasd","category":"Outer","price":"asdasdasdasdasd"},{"id":"1727848197782","productName":"asdasdasd","category":"Outer","price":"asdasdasdasdasd"},{"id":"1727848197935","productName":"asdasdasd","category":"Outer","price":"asdasdasdasdasd"},{"id":"1727848198099","productName":"asdasdasd","category":"Outer","price":"asdasdasdasdasd"},{"id":"1727848198232","productName":"asdasdasd","category":"Outer","price":"asdasdasdasdasd"},{"id":"1727848198382","productName":"asdasdasd","category":"Outer","price":"asdasdasdasdasd"},{"id":"1727848198550","productName":"asdasdasd","category":"Outer","price":"asdasdasdasdasd"},{"id":"1727848200365","productName":"asdasdasd","category":"Outer","price":"asdasdasdasdasd"},{"id":"1727848200493","productName":"asdasdasd","category":"Outer","price":"asdasdasdasdasd"},{"id":"1727848200798","productName":"asdasdasd","category":"Outer","price":"asdasdasdasdasd"},{"id":"1727848264908","productName":"sds","category":"Pants","price":"66"},{"id":"1727848281791","productName":"sds","category":"Pants","price":"66"},{"id":"1727848293489","productName":"asdasd","category":"Outer","price":"5555"},{"id":"1727848357720","productName":"ttttt","category":"Outer","price":"9999"},{"id":"1727848395930","productName":"ttttt","category":"Outer","price":"9999"},{"id":"1727848396502","productName":"ttttt","category":"Outer","price":"9999"},{"id":"1727848396785","productName":"ttttt","category":"Outer","price":"9999"},{"id":"1727848396951","productName":"ttttt","category":"Outer","price":"9999"},{"id":"1727848397121","productName":"ttttt","category":"Outer","price":"9999"},{"id":"1727848397270","productName":"ttttt","category":"Outer","price":"9999"},{"id":"1727848397435","productName":"ttttt","category":"Outer","price":"9999"},{"id":"1727848397601","productName":"ttttt","category":"Outer","price":"9999"},{"id":"1727848400602","productName":"ttttt","category":"Shoes","price":"9999"},{"id":"1727848400747","productName":"ttttt","category":"Shoes","price":"9999"},{"id":"1727848401071","productName":"ttttt","category":"Shoes","price":"9999"},{"id":"1727848411441","productName":"ttttt","category":"Shoes","price":"9999"},{"id":"1727848411604","productName":"ttttt","category":"Shoes","price":"9999"},{"id":"1727848411754","productName":"ttttt","category":"Shoes","price":"9999"},{"id":"1727848411886","productName":"ttttt","category":"Shoes","price":"9999"},{"id":"1727848412055","productName":"ttttt","category":"Shoes","price":"9999"},{"id":"1727848412204","productName":"ttttt","category":"Shoes","price":"9999"}]